ipinfo_cli/__init__.py
ipinfo_cli/main.py
ipinfo_cli-0.1.4.dist-info/METADATA
ipinfo_cli-0.1.4.dist-info/WHEEL
ipinfo_cli-0.1.4.dist-info/entry_points.txt
ipinfo_cli-0.1.4.dist-info/top_level.txt
ipinfo_cli-0.1.4.dist-info/RECORD
