Metadata-Version: 2.1
Name: ipinfo-cli
Version: 0.1.4
Summary: A CLI tool for getting information about an IP address using ipinfo.io
Home-page: https://github.com/cyclothymia/ipinfo-cli
Author: cyclothymia
Author-email: pr0jared@proton.me
License: MIT
Requires-Dist: requests
Requires-Dist: colorama
Requires-Dist: cryptography
